brrrData/__init__.py
brrrData/__main__.py
brrrData/file_selection.py
brrrData/data_processing/__init__.py
brrrData/data_processing/comparison.py
brrrData/data_processing/duplicate_handling.py
brrrData/data_processing/modification.py
brrrData/data_processing/sorting.py
brrrData/utils/prompt_utils.py
brrrdata-0.2.0.dist-info/LICENSE
brrrdata-0.2.0.dist-info/METADATA
brrrdata-0.2.0.dist-info/WHEEL
brrrdata-0.2.0.dist-info/entry_points.txt
brrrdata-0.2.0.dist-info/top_level.txt
brrrdata-0.2.0.dist-info/RECORD
